qcaus/__init__.py
qcaus-0.0.0.dist-info/LICENSE
qcaus-0.0.0.dist-info/METADATA
qcaus-0.0.0.dist-info/WHEEL
qcaus-0.0.0.dist-info/top_level.txt
qcaus-0.0.0.dist-info/RECORD
